Workbook

Sheet Dashboard
B2: PROSPECTIVE CUSTOMER & SALES LEAD TRACKING SYSTEM
B3: BDR Sales Operations & Executive Pipeline Intelligence | Portfolio Project for AuthBridge Research Services
B5: TOTAL LEADS | D5: TOTAL POTENTIAL PIPELINE VALUE | G5: CONVERTED REVENUE | I5: CONVERSION RATE | K5: OVERDUE FOLLOW-UPS
B6: =COUNTA('Lead Tracker'!A2:A21) | D6: =SUMIF('Lead Tracker'!H2:H21, "<>Lost", 'Lead Tracker'!G2:G21) | G6: =SUMIF('Lead Tracker'!H2:H21, "Converted", 'Lead Tracker'!G2:G21) | I6: =COUNTIF('Lead Tracker'!H2:H21, "Converted")/COUNTA('Lead Tracker'!A2:A21) | K6: =COUNTIFS('Lead Tracker'!J2:J21, "<"&TODAY(), 'Lead Tracker'!J2:J21, ">0", 'Lead Tracker'!H2:H21, "<>Converted", 'Lead Tracker'!H2:H21, "<>Lost")
B7: Total Tracked Prospects | D7: Active Pipeline (Excl. Lost) | G7: Won Deals Closed Value | I7: Converted / Total Leads | K7: Requires Immediate Outreach
B9: SALES PIPELINE FUNNEL & STAGE VOLUME BREAKDOWN
B10: NEW LEADS | C10: CONTACTED | D10: INTERESTED LEADS | F10: QUALIFIED LEADS | H10: MEETINGS SCHEDULED | J10: PROPOSALS SENT | L10: CONVERTED | M10: LOST LEADS
B11: =COUNTIF('Lead Tracker'!H2:H21, "New Lead") | C11: =COUNTIF('Lead Tracker'!H2:H21, "Contacted") | D11: =COUNTIF('Lead Tracker'!H2:H21, "Interested") | F11: =COUNTIF('Lead Tracker'!H2:H21, "Qualified") | H11: =COUNTIF('Lead Tracker'!H2:H21, "Meeting Scheduled") | J11: =COUNTIF('Lead Tracker'!H2:H21, "Proposal Sent") | L11: =COUNTIF('Lead Tracker'!H2:H21, "Converted") | M11: =COUNTIF('Lead Tracker'!H2:H21, "Lost")
B13: SALES PIPELINE STAGE BREAKDOWN | I13: LEAD SOURCE PERFORMANCE & CHANNELS
B14: Lead Status / Stage | C14: Leads | D14: Pipeline Value (₹) | E14: Avg Deal Size (₹) | F14: Stage Share % | I14: Lead Source | J14: Total Leads | K14: Won Leads | L14: Win Rate % | M14: Total Budget (₹)
B15: New Lead | C15: =COUNTIF('Lead Tracker'!$H$2:$H$21, "New Lead") | D15: =SUMIF('Lead Tracker'!$H$2:$H$21, "New Lead", 'Lead Tracker'!$G$2:$G$21) | E15: =IFERROR(D15/C15, 0) | F15: =IFERROR(C15/$C$23, 0) | I15: LinkedIn | J15: =COUNTIF('Lead Tracker'!$E$2:$E$21, "LinkedIn") | K15: =COUNTIFS('Lead Tracker'!$E$2:$E$21, "LinkedIn", 'Lead Tracker'!$H$2:$H$21, "Converted") | L15: =IFERROR(K15/J15, 0) | M15: =SUMIF('Lead Tracker'!$E$2:$E$21, "LinkedIn", 'Lead Tracker'!$G$2:$G$21)
B16: Contacted | C16: =COUNTIF('Lead Tracker'!$H$2:$H$21, "Contacted") | D16: =SUMIF('Lead Tracker'!$H$2:$H$21, "Contacted", 'Lead Tracker'!$G$2:$G$21) | E16: =IFERROR(D16/C16, 0) | F16: =IFERROR(C16/$C$23, 0) | I16: Email | J16: =COUNTIF('Lead Tracker'!$E$2:$E$21, "Email") | K16: =COUNTIFS('Lead Tracker'!$E$2:$E$21, "Email", 'Lead Tracker'!$H$2:$H$21, "Converted") | L16: =IFERROR(K16/J16, 0) | M16: =SUMIF('Lead Tracker'!$E$2:$E$21, "Email", 'Lead Tracker'!$G$2:$G$21)
B17: Interested | C17: =COUNTIF('Lead Tracker'!$H$2:$H$21, "Interested") | D17: =SUMIF('Lead Tracker'!$H$2:$H$21, "Interested", 'Lead Tracker'!$G$2:$G$21) | E17: =IFERROR(D17/C17, 0) | F17: =IFERROR(C17/$C$23, 0) | I17: Cold Call | J17: =COUNTIF('Lead Tracker'!$E$2:$E$21, "Cold Call") | K17: =COUNTIFS('Lead Tracker'!$E$2:$E$21, "Cold Call", 'Lead Tracker'!$H$2:$H$21, "Converted") | L17: =IFERROR(K17/J17, 0) | M17: =SUMIF('Lead Tracker'!$E$2:$E$21, "Cold Call", 'Lead Tracker'!$G$2:$G$21)
B18: Qualified | C18: =COUNTIF('Lead Tracker'!$H$2:$H$21, "Qualified") | D18: =SUMIF('Lead Tracker'!$H$2:$H$21, "Qualified", 'Lead Tracker'!$G$2:$G$21) | E18: =IFERROR(D18/C18, 0) | F18: =IFERROR(C18/$C$23, 0) | I18: Referral | J18: =COUNTIF('Lead Tracker'!$E$2:$E$21, "Referral") | K18: =COUNTIFS('Lead Tracker'!$E$2:$E$21, "Referral", 'Lead Tracker'!$H$2:$H$21, "Converted") | L18: =IFERROR(K18/J18, 0) | M18: =SUMIF('Lead Tracker'!$E$2:$E$21, "Referral", 'Lead Tracker'!$G$2:$G$21)
B19: Meeting Scheduled | C19: =COUNTIF('Lead Tracker'!$H$2:$H$21, "Meeting Scheduled") | D19: =SUMIF('Lead Tracker'!$H$2:$H$21, "Meeting Scheduled", 'Lead Tracker'!$G$2:$G$21) | E19: =IFERROR(D19/C19, 0) | F19: =IFERROR(C19/$C$23, 0) | I19: Website | J19: =COUNTIF('Lead Tracker'!$E$2:$E$21, "Website") | K19: =COUNTIFS('Lead Tracker'!$E$2:$E$21, "Website", 'Lead Tracker'!$H$2:$H$21, "Converted") | L19: =IFERROR(K19/J19, 0) | M19: =SUMIF('Lead Tracker'!$E$2:$E$21, "Website", 'Lead Tracker'!$G$2:$G$21)
B20: Proposal Sent | C20: =COUNTIF('Lead Tracker'!$H$2:$H$21, "Proposal Sent") | D20: =SUMIF('Lead Tracker'!$H$2:$H$21, "Proposal Sent", 'Lead Tracker'!$G$2:$G$21) | E20: =IFERROR(D20/C20, 0) | F20: =IFERROR(C20/$C$23, 0) | I20: Total Channels | J20: =SUM(J15:J19) | K20: =SUM(K15:K19) | L20: =IFERROR(K20/J20, 0) | M20: =SUM(M15:M19)
B21: Converted | C21: =COUNTIF('Lead Tracker'!$H$2:$H$21, "Converted") | D21: =SUMIF('Lead Tracker'!$H$2:$H$21, "Converted", 'Lead Tracker'!$G$2:$G$21) | E21: =IFERROR(D21/C21, 0) | F21: =IFERROR(C21/$C$23, 0)
B22: Lost | C22: =COUNTIF('Lead Tracker'!$H$2:$H$21, "Lost") | D22: =SUMIF('Lead Tracker'!$H$2:$H$21, "Lost", 'Lead Tracker'!$G$2:$G$21) | E22: =IFERROR(D22/C22, 0) | F22: =IFERROR(C22/$C$23, 0)
B23: Total / Portfolio Summary | C23: =SUM(C15:C22) | D23: =SUM(D15:D22) | E23: =IFERROR(D23/C23, 0) | F23: =SUM(F15:F22)

Sheet Lead Tracker
A1: Lead ID | B1: Customer Name | C1: Company Name | D1: Contact Number | E1: Lead Source | F1: Interested Service | G1: Estimated Budget (₹) | H1: Lead Status | I1: Last Contact Date | J1: Next Follow-up Date | K1: Remarks
A2: L-1001 | B2: Rajesh Sharma | C2: Flipkart Internet Pvt Ltd | D2: +91 98201 45678 | E2: LinkedIn | F2: Employee Background Verification | G2: 1450000 | H2: Proposal Sent | I2: 46307 | J2: 46310 | K2: Sent commercial proposal for 4,500 annual white-collar candidate checks; awaiting CFO sign-off.
A3: L-1002 | B3: Priya Nair | C3: Swiggy (Bundl Technologies) | D3: +91 98112 34567 | E3: Website | F3: Digital Address Verification | G3: 2200000 | H3: Qualified | I3: 46309 | J3: 46316 | K3: High interest in contactless GPS-geotagged address verification for 15,000 pan-India fleet partners.
A4: L-1003 | B4: Amit Verma | C4: Razorpay Payments Ltd | D4: +91 98334 11223 | E4: Referral | F4: Instant KYC & Digital ID Suite | G4: 1850000 | H4: Converted | I4: 46300 | K4: Contract executed for automated merchant onboarding API, Aadhaar OCR, and bank account validation.
A5: L-1004 | B5: Sneha Patel | C5: Infosys Technologies Ltd | D5: +91 98450 99887 | E5: Email | F5: Employee Background Verification | G5: 3500000 | H5: Meeting Scheduled | I5: 46311 | J5: 46317 | K5: Product demo booked with Talent Acquisition VP and Compliance Director regarding fast-track BGV API.
A6: L-1005 | B6: Vikram Singhania | C6: Tata 1mg Healthcare | D6: +91 98101 66554 | E6: Cold Call | F6: Vendor Due Diligence | G6: 650000 | H6: Contacted | I6: 46308 | J6: 46315 | K6: Spoke with Head of Procurement; shared technical brochure on supply chain and pharmacy vendor risk screening.
A7: L-1006 | B7: Ananya Iyer | C7: Zomato Media Pvt Ltd | D7: +91 98710 44332 | E7: LinkedIn | F7: Workforce & Blue-Collar Verification | G7: 1950000 | H7: Proposal Sent | I7: 46305 | J7: 46309 | K7: Follow-up required on RFP submission for criminal and identity checks across delivery personnel.
A8: L-1007 | B8: Rohan Kapoor | C8: Delhivery Logistics | D8: +91 99100 88776 | E8: Website | F8: Criminal & Court Records Search | G8: 1200000 | H8: Interested | I8: 46310 | J8: 46318 | K8: Requested technical architecture specs on automated e-Courts search and nationwide police record checks.
A9: L-1008 | B9: Neha Gupta | C9: Urban Company | D9: +91 98220 33445 | E9: Referral | F9: Instant KYC & Digital ID Suite | G9: 850000 | H9: Converted | I9: 46293 | K9: Closed annual agreement for service professional biometric KYC and document verification.
A10: L-1009 | B10: Siddharth Mehta | C10: One97 Communications (Paytm) | D10: +91 98188 77665 | E10: Cold Call | F10: AML & Financial Sanctions Screening | G10: 1600000 | H10: Qualified | I10: 46306 | J10: 46319 | K10: Passed BANT qualification; requirements mapped to AuthBridge PEP, Interpol, and global sanctions API.
A11: L-1010 | B11: Kavita Reddy | C11: Pine Labs Pvt Ltd | D11: +91 98480 22334 | E11: LinkedIn | F11: API Onboarding & OCR Suite | G11: 950000 | H11: Interested | I11: 46303 | J11: 46311 | K11: Evaluating optical character recognition (OCR) speed and accuracy benchmark against incumbent provider.
A12: L-1011 | B12: Arpit Bansal | C12: Unacademy EdTech | D12: +91 99300 55667 | E12: Email | F12: Education & Credential Check | G12: 450000 | H12: Lost | I12: 46297 | K12: Paused all external hiring screening integrations due to internal organization budget freeze.
A13: L-1012 | B13: Pooja Joshi | C13: Groww (Nextbillion Tech) | D13: +91 98205 11998 | E13: Website | F13: Instant KYC & Digital ID Suite | G13: 2100000 | H13: Meeting Scheduled | I13: 46312 | J13: 46320 | K13: Demo scheduled with VP of Customer Onboarding for SEBI/KRA compliant digital verification suite.
A14: L-1013 | B14: Manish Agarwal | C14: Zepto (KiranaKart) | D14: +91 98115 66778 | E14: Cold Call | F14: Workforce & Blue-Collar Verification | G14: 1750000 | H14: New Lead | I14: 46311 | J14: 46314 | K14: Lead generated from dark-store network expansion news; introductory BDR outreach drafted.
A15: L-1014 | B15: Tarun Batra | C15: CRED (Dreamplug Tech) | D15: +91 98199 44556 | E15: Referral | F15: Executive Due Diligence | G15: 780000 | H15: Qualified | I15: 46304 | J15: 46316 | K15: VP Risk approved technical scope for C-suite and leadership background due diligence.
A16: L-1015 | B16: Divya Sundaram | C16: Shadowfax Technologies | D16: +91 98455 33221 | E16: LinkedIn | F16: Digital Address Verification | G16: 1300000 | H16: Contacted | I16: 46306 | J16: 46313 | K16: Spoke with Logistics Partner Operations Manager; sent comparative turnaround-time (TAT) performance report.
A17: L-1016 | B17: Nitin Saxena | C17: Ather Energy | D17: +91 98212 99001 | E17: Email | F17: Vendor Due Diligence | G17: 520000 | H17: Lost | I17: 46290 | K17: Decided to renew with incumbent local vendor citing multi-year volume commitment lock-in.
A18: L-1017 | B18: Swati Deshmukh | C18: Meesho Online Marketplace | D18: +91 98104 12345 | E18: Website | F18: Instant KYC & Digital ID Suite | G18: 2400000 | H18: Interested | I18: 46309 | J18: 46317 | K18: High volume seller onboarding verification inquiry; requested developer sandbox environment access.
A19: L-1018 | B19: Gaurav Chopra | C19: Nykaa E-Retail Ltd | D19: +91 98765 43210 | E19: LinkedIn | F19: Employee Background Verification | G19: 1150000 | H19: New Lead | I19: 46312 | J19: 46315 | K19: Connected with Assistant Director HR on LinkedIn; preparing customized corporate presentation deck.
A20: L-1019 | B20: Meghna Sen | C20: Spinny Car Hub | D20: +91 99201 88223 | E20: Cold Call | F20: Criminal & Court Records Search | G20: 600000 | H20: Contacted | I20: 46307 | J20: 46311 | K20: Follow-up call scheduled regarding driver and vehicle inspector background checks.
A21: L-1020 | B21: Rahul Kulkarni | C21: PolicyBazaar Insurance | D21: +91 98180 55443 | E21: Email | F21: AML & Financial Sanctions Screening | G21: 1400000 | H21: New Lead | I21: 46313 | J21: 46318 | K21: Outbound BDR sequence initiated focusing on IRDAI anti-fraud compliance and agent onboarding rules.

Sheet Instructions
B2: SYSTEM DOCUMENTATION & BDR USER MANUAL
B3: Operating Manual for Prospective Account Tracking, Qualification, Pipeline Hygiene, and Analytics
B5: 1. PURPOSE & WORKBOOK ARCHITECTURE
B6: Project Objective & Purpose | D6: Developed as an executive sales operations portfolio project for the Business Development Representative (BDR) Intern application at AuthBridge Research Services Pvt. Ltd. Demonstrates full-cycle prospecting management, pipeline analytics, and data hygiene.
B7: B2B Verification Domain Fit | D7: Tailored to AuthBridge's product suite: Employee Background Verification (BGV), Instant KYC & Digital ID, Workforce/Blue-Collar Screening, Vendor Due Diligence, Criminal & Court Records Search, and API Integrations.
B8: Architecture & Three Sheets | D8: • 'Dashboard': Executive summary KPIs, stage funnel mini-cards, distribution tables, and dynamic charts. • 'Lead Tracker': Transactional Excel table featuring data validation, conditional formatting, and autofilters. • 'Instructions': Standard operating procedures, BANT framework, and KPI glossary.
B10: 2. HOW TO USE THE LEAD TRACKER (DAILY BDR WORKFLOW)
B11: Step 1: Adding a Prospective Lead | D11: Open 'Lead Tracker'. Add a new row to the table. Assign a sequential Lead ID (e.g. L-1021), enter Customer Name, Company Name, and Contact Number. The Excel table automatically expands formatting and formulas.
B12: Step 2: Assigning Lead Source & Service | D12: Select the channel from the dropdown (LinkedIn, Email, Cold Call, Referral, Website). Enter the specific AuthBridge solution and estimated contract budget in INR (₹).
B13: Step 3: Managing Pipeline Status | D13: Update Lead Status as discussions advance: New Lead -> Contacted -> Interested -> Qualified -> Meeting Scheduled -> Proposal Sent -> Converted / Lost. Always select from the dropdown to ensure dashboard accuracy.
B14: Step 4: Scheduling Follow-ups | D14: Enter 'Last Contact Date' and 'Next Follow-up Date' (format: YYYY-MM-DD). If a follow-up date passes without an update, the cell triggers an automated visual alert and increments the Overdue KPI on the Dashboard.
B16: 3. DATA VALIDATION & DROPDOWN GLOSSARY
B17: Lead Source Dropdown | D17: • LinkedIn: Targeted InMail & social selling to HR/Risk heads. • Email: Cold outbound email campaigns & sequences. • Cold Call: Direct telephone outreach to key decision makers. • Referral: Inbound introductions from clients or business partners. • Website: Inbound demo requests and enterprise contact forms.
B18: Lead Status Progression | D18: • New Lead: Uncontacted prospect identified from industry research. • Contacted: Initial touchpoint made; awaiting prospect response. • Interested: Prospect expressed interest in AuthBridge capabilities. • Qualified: Passed BANT criteria (Budget, Authority, Need, Timeline). • Meeting Scheduled: Technical discovery or product demo booked. • Proposal Sent: Commercial quotation and SLA proposal shared. • Converted: Contract signed / closed-won customer account. • Lost: Disqualified, deal lost to competitor, or cancelled project.
B19: Input Protection | D19: In-cell data validation restricts values to authorized options, eliminating spelling errors that could distort analytics.
B21: 4. CONDITIONAL FORMATTING LOGIC & VISUAL ALERTS
B22: Overdue Follow-up Alert (Red) | D22: Highlights Next Follow-up Date in soft coral with bold red text if: Next Follow-up Date < TODAY() AND Status is not 'Converted' or 'Lost'. Serves as an immediate prompt to contact the client.
B23: Converted Lead Highlight (Green) | D23: Highlights the Lead Status cell in soft mint green when marked 'Converted', providing instant visual feedback for closed-won revenue.
B24: Lost Lead Highlight (Gray) | D24: Formats the Lead Status cell in soft neutral gray when marked 'Lost' to indicate inactive deals without cluttering the active pipeline.
B25: Handling Closed Leads | D25: For Converted or Lost accounts, leave the 'Next Follow-up Date' empty. The alert formula ignores blank cells.
B27: 5. DASHBOARD FORMULA & ANALYTICS REFERENCE
B28: Total Leads | D28: =COUNTA('Lead Tracker'!A2:A21). Total number of prospective accounts logged in the tracker.
B29: Total Potential Pipeline Value | D29: =SUMIF('Lead Tracker'!H2:H21, "<>Lost", 'Lead Tracker'!G2:G21). Total active monetary pipeline excluding closed-lost deals.
B30: Conversion Rate % | D30: =COUNTIF('Lead Tracker'!H2:H21, "Converted")/COUNTA('Lead Tracker'!A2:A21). Closed-won deal percentage.
B31: Overdue Follow-ups Count | D31: =COUNTIFS('Lead Tracker'!J2:J21, "<"&TODAY(), 'Lead Tracker'!J2:J21, ">0", 'Lead Tracker'!H2:H21, "<>Converted", 'Lead Tracker'!H2:H21, "<>Lost"). Real-time count of leads requiring urgent outreach today.
B32: Interactive Charts | D32: • Chart 1 (Doughnut): Proportional distribution of leads across all 8 pipeline stages. • Chart 2 (Column): Total pipeline monetary value (INR) mapped across each stage.
B34: 6. BDR SALES PLAYBOOK & BANT QUALIFICATION (AUTHBRIDGE)
B35: Budget (B) | D35: Validate annual spend capability. (AuthBridge enterprise verification packages typically range from ₹3,00,000 to ₹35,00,000+ depending on volume).
B36: Authority (A) | D36: Engage primary decision-makers: VP/Director of Talent Acquisition, Chief Risk Officer (CRO), Compliance Head, or Chief Technology Officer (CTO).
B37: Need (N) | D37: Uncover core verification challenges: slow turnaround time (TAT), manual verification bottlenecks, regulatory compliance (SEBI/RBI/IRDAI), or high gig-worker fraud risk.
B38: Timeline (T) | D38: Identify hiring surge windows, incumbent vendor renewal deadlines, or target go-live dates for API integration.
